Metadata-Version: 2.4
Name: mathy_envs
Version: 0.12.5
Summary: Learning environments for solving math problems step-by-step
Home-page: https://mathy.ai
Author: Justin DuJardin
Author-email: justin@dujardinconsulting.com
License: All rights reserved
Keywords: math
Classifier: Programming Language :: Python :: 3
Classifier: License :: OSI Approved :: MIT License
Classifier: Operating System :: OS Independent
Classifier: Development Status :: 2 - Pre-Alpha
Requires-Python: >=3.7
License-File: LICENSE.md
Requires-Dist: numpy
Requires-Dist: colr
Requires-Dist: wasabi
Requires-Dist: mathy_core>=0.8.6
Requires-Dist: gym<0.26.0
Provides-Extra: dev
Requires-Dist: mypy; extra == "dev"
Requires-Dist: pytest; extra == "dev"
Requires-Dist: pytest-cov; extra == "dev"
Requires-Dist: black; extra == "dev"
Requires-Dist: flake8; extra == "dev"
Requires-Dist: isort; extra == "dev"
Requires-Dist: autoflake; extra == "dev"
Requires-Dist: mock; extra == "dev"
Requires-Dist: gymnasium; extra == "dev"
Provides-Extra: gym
Requires-Dist: gymnasium; extra == "gym"
Provides-Extra: all
Requires-Dist: mypy; extra == "all"
Requires-Dist: pytest; extra == "all"
Requires-Dist: pytest-cov; extra == "all"
Requires-Dist: black; extra == "all"
Requires-Dist: flake8; extra == "all"
Requires-Dist: isort; extra == "all"
Requires-Dist: autoflake; extra == "all"
Requires-Dist: mock; extra == "all"
Requires-Dist: gymnasium; extra == "all"
Requires-Dist: gymnasium; extra == "all"
Dynamic: author
Dynamic: author-email
Dynamic: classifier
Dynamic: description
Dynamic: description-content-type
Dynamic: home-page
Dynamic: keywords
Dynamic: license
Dynamic: license-file
Dynamic: provides-extra
Dynamic: requires-dist
Dynamic: requires-python
Dynamic: summary
